{
  "collectionName": "components_shared_testimonials",
  "info": {
    "displayName": "Testimonial",
    "icon": "quote-right",
    "description": ""
  },
  "options": {},
  "attributes": {
    "name": {
      "type": "string",
      "required": true
    },
    "designation": {
      "type": "string",
      "required": true
    },
    "review": {
      "type": "text",
      "required": true
    },
    "rating": {
      "type": "integer",
      "required": true
    },
    "image": {
      "type": "media",
      "multiple": false,
      "required": false,
      "allowedTypes": [
        "images"
      ]
    }
  }
}
